merge_subtitles/__init__.py
merge_subtitles/main.py
merge_subtitles-1.0.0.dist-info/licenses/LICENSE
tests/__init__.py
tests/test_merge_subtitles.py
merge_subtitles-1.0.0.dist-info/METADATA
merge_subtitles-1.0.0.dist-info/WHEEL
merge_subtitles-1.0.0.dist-info/entry_points.txt
merge_subtitles-1.0.0.dist-info/top_level.txt
merge_subtitles-1.0.0.dist-info/RECORD
