Metadata-Version: 2.4
Name: merge-subtitles
Version: 1.0.0
Summary: A tool for merging MP4 video files with SRT subtitle files into MKV format
Home-page: https://github.com/lorenzowood/merge-subtitles
Author: Lorenzo Wood
Author-email: Lorenzo Wood <lorenzo@lorenzowood.com>
Project-URL: Homepage, https://github.com/lorenzowood/merge-subtitles
Project-URL: Bug Reports, https://github.com/lorenzowood/merge-subtitles/issues
Project-URL: Source, https://github.com/lorenzowood/merge-subtitles
Keywords: video,subtitles,ffmpeg,mp4,srt,mkv,conversion
Classifier: Development Status :: 5 - Production/Stable
Classifier: Intended Audience :: End Users/Desktop
Classifier: Topic :: Multimedia :: Video :: Conversion
Classifier: License :: OSI Approved :: MIT License
Classifier: Programming Language :: Python :: 3
Classifier: Programming Language :: Python :: 3.7
Classifier: Programming Language :: Python :: 3.8
Classifier: Programming Language :: Python :: 3.9
Classifier: Programming Language :: Python :: 3.10
Classifier: Programming Language :: Python :: 3.11
Classifier: Programming Language :: Python :: 3.12
Classifier: Operating System :: OS Independent
Classifier: Environment :: Console
Requires-Python: >=3.7
License-File: LICENSE
Provides-Extra: dev
Requires-Dist: pytest>=7.0.0; extra == "dev"
Requires-Dist: pytest-mock>=3.10.0; extra == "dev"
Dynamic: author
Dynamic: home-page
Dynamic: license-file
Dynamic: requires-python
